lcurl/__init__.py
lcurl-0.1.0.dist-info/WHEEL
lcurl-0.1.0.dist-info/entry_points.txt
lcurl-0.1.0.dist-info/METADATA
lcurl-0.1.0.dist-info/RECORD
