Metadata-Version: 2.3
Name: lcurl
Version: 0.1.0
Summary: Fundamental package for cURL transfers in Python.
Keywords: cpython,curl,cython,download,extension module,file transfer,http3,https3,libcurl,network protocols,requests,requests,scp,scraping,sftp,trurl,upload,url transfer,urllib,wget
Author: Faddeev-Popov
Author-email: Faddeev-Popov <faddeev-popov@proton.me>
License: MIT License
Classifier: Development Status :: 1 - Planning
Classifier: Environment :: Web Environment
Classifier: Framework :: AsyncIO
Classifier: Intended Audience :: Developers
Classifier: Intended Audience :: Information Technology
Classifier: Intended Audience :: Telecommunications Industry
Classifier: License :: OSI Approved :: MIT License
Classifier: Operating System :: POSIX :: Linux
Classifier: Programming Language :: C
Classifier: Programming Language :: Cython
Classifier: Programming Language :: Perl
Classifier: Programming Language :: Python :: 3.13
Classifier: Programming Language :: Python :: Implementation :: CPython
Classifier: Programming Language :: Unix Shell
Classifier: Topic :: Internet :: File Transfer Protocol (FTP)
Classifier: Topic :: Internet :: Name Service (DNS)
Classifier: Topic :: Internet :: Proxy Servers
Classifier: Topic :: Internet :: WWW/HTTP
Classifier: Topic :: Internet
Classifier: Topic :: Software Development :: Libraries
Classifier: Topic :: System :: Benchmark
Classifier: Topic :: System :: Networking
Classifier: Typing :: Typed
Requires-Dist: libcurl-ext
Requires-Python: >=3.13
